MBCMusicCrawler/MBCMusicCrawler.py
MBCMusicCrawler/__init__.py
MBCMusicCrawler/constants.py
MBCMusicCrawler-0.0.1.dist-info/METADATA
MBCMusicCrawler-0.0.1.dist-info/WHEEL
MBCMusicCrawler-0.0.1.dist-info/top_level.txt
MBCMusicCrawler-0.0.1.dist-info/RECORD
