Metadata-Version: 2.1
Name: MBCMusicCrawler
Version: 0.0.1
Summary: Crawl Music List From MBC Radio
Home-page: https://github.com/opendev-choi/mbc-radio-music-crawler
Author: opendev.choi
Author-email: opendev.choi@gmail.com
License: UNKNOWN
Platform: UNKNOWN
Requires-Dist: cython
